streamlit_carousel_slider/__init__.py
streamlit_carousel_slider/frontend/dist/index.html
streamlit_carousel_slider/frontend/dist/assets/index-BBmrR8-p.css
streamlit_carousel_slider/frontend/dist/assets/index-BWXurFek.js
streamlit_carousel_slider/frontend/dist/assets/index-CAzZG-zn.js
streamlit_carousel_slider/frontend/dist/assets/index-COYXmUEG.css
streamlit_carousel_slider/frontend/dist/assets/index-D79J4LZk.css
streamlit_carousel_slider/frontend/dist/assets/index-Dlgziywx.js
streamlit_carousel_slider/frontend/dist/assets/index-E5u4M8Qm.js
streamlit_carousel_slider/frontend/dist/assets/index-EPdemtcJ.css
streamlit_carousel_slider-1.3.0.dist-info/LICENSE
streamlit_carousel_slider-1.3.0.dist-info/METADATA
streamlit_carousel_slider-1.3.0.dist-info/WHEEL
streamlit_carousel_slider-1.3.0.dist-info/top_level.txt
streamlit_carousel_slider-1.3.0.dist-info/RECORD
