Metadata-Version: 2.1
Name: streamlit-carousel-slider
Version: 1.3.0
Summary: Carousel slider component for streamlit using React and tailwind with daisyui.
Home-page: https://pypi.org/project/streamlit-carousel-slider
Author: ryone9re
Author-email: ryoichi.kurimoto@gmail.com
Requires-Python: >=3.12
License-File: LICENSE
Requires-Dist: streamlit >=1.40
